{
  "data": [
    {
      "mode": "markers",
      "name": "<br>",
      "type": "choropleth",
      "zmax": 46.2364532,
      "zmin": 0.009852216749,
      "zsrc": "aline_interviewingio:1108:724e54",
      "z": [
        "0.09852216749",
        "0.08866995074",
        "0.4334975369",
        "46.2364532",
        "0.5615763547",
        "0.3054187192",
        "0.6896551724",
        "0.09852216749",
        "0.9556650246",
        "0.7783251232",
        "0.0197044335",
        "0.157635468",
        "0.039408867",
        "1.556650246",
        "0.2955665025",
        "0.009852216749",
        "0.08866995074",
        "0.157635468",
        "0.06896551724",
        "6.285714286",
        "0.7487684729",
        "0.02955665025",
        "0.3645320197",
        "0.3743842365",
        "0.2660098522",
        "0.02955665025",
        "0.8669950739",
        "0.009852216749",
        "0.4926108374",
        "0.1280788177",
        "1.507389163",
        "0.0197044335",
        "0.09852216749",
        "13.74384236",
        "0.39408867",
        "0.02955665025",
        "0.5615763547",
        "1.261083744",
        "0.1674876847",
        "0.06896551724",
        "0.009852216749",
        "0.197044335",
        "3.192118227",
        "0.236453202",
        "0.5714285714",
        "0.02955665025",
        "15.45812808",
        "0.1871921182",
        "0.0197044335",
        "0.009852216749"
      ],
      "zauto": false,
      "colorscale": [
        [
          0,
          "#ffffcc"
        ],
        [
          0.125,
          "#ffeda0"
        ],
        [
          0.25,
          "#fed976"
        ],
        [
          0.375,
          "#feb24c"
        ],
        [
          0.5,
          "#fd8d3c"
        ],
        [
          0.625,
          "#fc4e2a"
        ],
        [
          0.75,
          "#e31a1c"
        ],
        [
          0.875,
          "#bd0026"
        ],
        [
          1,
          "#800026"
        ]
      ],
      "locationmode": "USA-states",
      "locationssrc": "aline_interviewingio:1108:59fd07",
      "locations": [
        "AL",
        "AR",
        "AZ",
        "CA",
        "CO",
        "CT",
        "DC",
        "DE",
        "FL",
        "GA",
        "HI",
        "IA",
        "ID",
        "IL",
        "IN",
        "Ka",
        "KS",
        "KY",
        "LA",
        "MA",
        "MD",
        "ME",
        "MI",
        "MN",
        "MO",
        "MS",
        "NC",
        "ND",
        "NE",
        "NH",
        "NJ",
        "NM",
        "NV",
        "NY",
        "OH",
        "OK",
        "OR",
        "PA",
        "RI",
        "SC",
        "SD",
        "TN",
        "TX",
        "UT",
        "VA",
        "VT",
        "WA",
        "WI",
        "WV",
        "WY"
      ],
      "autocolorscale": false
    }
  ],
  "frames": [],
  "layout": {
    "geo": {
      "scope": "usa",
      "center": {},
      "showland": true,
      "showlakes": false,
      "projection": {},
      "showsubunits": true,
      "showcountries": true
    },
    "xaxis": {
      "range": [
        -1,
        6
      ],
      "autorange": true
    },
    "yaxis": {
      "range": [
        -1,
        4
      ],
      "autorange": true
    },
    "autosize": true,
    "showlegend": true
  }
}