{
  "data": [
    {
      "uid": "8050d4",
      "name": "round",
      "type": "histogram",
      "xsrc": "aline_interviewingio:33:NLICVTWX9HEUJD8ZZQV3Q2IQ3Q4G582K",
      "x": [
        0.03,
        0.04,
        0.05,
        0.05,
        0.05,
        0.06,
        0.07,
        0.07,
        0.07,
        0.07,
        0.09,
        0.09,
        0.1,
        0.12,
        0.14,
        0.16,
        0.17,
        0.17,
        0.18,
        0.2,
        0.23,
        0.24,
        0.26,
        0.27,
        0.28,
        0.29,
        0.29,
        0.3,
        0.37,
        0.37,
        0.38,
        0.38,
        0.41,
        0.46,
        0.46,
        0.52,
        0.53,
        0.56,
        0.56,
        0.6,
        0.63,
        0.64,
        0.68,
        0.69,
        0.71,
        0.76,
        0.86,
        0.87,
        0.88,
        0.96,
        1.2,
        1.24,
        1.27,
        1.31,
        1.37,
        1.39,
        1.44,
        1.49,
        1.52,
        1.64,
        1.71,
        1.9,
        1.98,
        2,
        2.06,
        2.15,
        2.17,
        2.18,
        2.28,
        2.35,
        2.42,
        2.44,
        2.52,
        2.54,
        3.04,
        3.19,
        3.32,
        3.47,
        3.58,
        3.67,
        3.82,
        3.82,
        4.12,
        4.33,
        4.53,
        5.25,
        5.31,
        5.4,
        5.47,
        5.53,
        5.64,
        5.72,
        6.03,
        6.06,
        6.65,
        6.72,
        6.8,
        6.86,
        6.9,
        7.05,
        7.23,
        7.94,
        8.06,
        8.39,
        8.45,
        8.86,
        9.33,
        10.07,
        10.57,
        11.09,
        11.12,
        11.62,
        12.07,
        12.15,
        12.4,
        13.4,
        14.03,
        14.13,
        14.29,
        14.77,
        16.02,
        16.49,
        16.93,
        17.21,
        28.17
      ],
      "xbins": {
        "end": 29,
        "size": 1,
        "start": 0
      },
      "autobinx": false,
      "histnorm": ""
    }
  ],
  "layout": {
    "title": "Interview Wait Times",
    "width": 936,
    "xaxis": {
      "type": "linear",
      "range": [
        0,
        29
      ],
      "title": "Wait time (minutes)",
      "autorange": true
    },
    "yaxis": {
      "type": "linear",
      "range": [
        0,
        52.631578947368425
      ],
      "title": "Frequency",
      "autorange": true
    },
    "bargap": 0.14,
    "height": 587,
    "autosize": true,
    "showlegend": false
  }
}